learning_machines_drift/__init__.py
learning_machines_drift/backends.py
learning_machines_drift/datasets.py
learning_machines_drift/display.py
learning_machines_drift/exceptions.py
learning_machines_drift/filter.py
learning_machines_drift/metrics.py
learning_machines_drift/monitor.py
learning_machines_drift/registry.py
learning_machines_drift/types.py
learning_machines_drift-0.0.3.dist-info/WHEEL
learning_machines_drift-0.0.3.dist-info/METADATA
learning_machines_drift-0.0.3.dist-info/RECORD
